[
  {
    "id": "png-jpg",
    "title": "PNG → JPG",
    "description": "PNG 이미지를 고품질 JPG 형식으로 변환합니다.",
    "icon": "🖼",
    "category": "image",
    "path": "converters/png-jpg/index.html",
    "status": "ready",
    "accept": [
      ".png"
    ],
    "output": "jpg",
    "sourceFormat": "PNG",
    "targetFormat": "JPG",
    "priority": 120,
    "generatedBy": "image-converter-registry",
    "accessLevel": "free",
    "trialAvailable": false,
    "audience": "일반 사용자",
    "featured": true
  },
  {
    "id": "png-webp",
    "title": "PNG → WEBP",
    "description": "PNG 이미지를 고품질 WEBP 형식으로 변환합니다.",
    "icon": "🖼",
    "category": "image",
    "path": "converters/png-webp/index.html",
    "status": "ready",
    "accept": [
      ".png"
    ],
    "output": "webp",
    "sourceFormat": "PNG",
    "targetFormat": "WEBP",
    "priority": 119,
    "generatedBy": "image-converter-registry",
    "accessLevel": "free",
    "trialAvailable": false,
    "audience": "일반 사용자",
    "featured": true
  },
  {
    "id": "png-jpeg",
    "title": "PNG → JPEG",
    "description": "PNG 이미지를 고품질 JPEG 형식으로 변환합니다.",
    "icon": "🖼",
    "category": "image",
    "path": "converters/png-jpeg/index.html",
    "status": "ready",
    "accept": [
      ".png"
    ],
    "output": "jpeg",
    "sourceFormat": "PNG",
    "targetFormat": "JPEG",
    "priority": 118.9,
    "generatedBy": "png-popular-pack-2",
    "accessLevel": "free",
    "trialAvailable": false,
    "audience": "일반 사용자",
    "featured": false
  },
  {
    "id": "png-pdf",
    "title": "PNG → PDF",
    "description": "여러 PNG 이미지를 한 개의 PDF 문서로 합칩니다.",
    "icon": "🖼",
    "category": "image",
    "path": "converters/png-pdf/index.html",
    "status": "ready",
    "accept": [
      ".png"
    ],
    "output": "pdf",
    "sourceFormat": "PNG",
    "targetFormat": "PDF",
    "priority": 118.8,
    "generatedBy": "png-popular-pack-2",
    "accessLevel": "free",
    "trialAvailable": false,
    "audience": "일반 사용자",
    "featured": true
  },
  {
    "id": "png-ico",
    "title": "PNG → ICO",
    "description": "PNG를 파비콘과 Windows 아이콘용 ICO로 변환합니다.",
    "icon": "🖼",
    "category": "image",
    "path": "converters/png-ico/index.html",
    "status": "ready",
    "accept": [
      ".png"
    ],
    "output": "ico",
    "sourceFormat": "PNG",
    "targetFormat": "ICO",
    "priority": 118.7,
    "generatedBy": "png-popular-pack-2",
    "accessLevel": "free",
    "trialAvailable": false,
    "audience": "일반 사용자",
    "featured": true
  },
  {
    "id": "png-gif",
    "title": "PNG → GIF",
    "description": "PNG를 정지 GIF 이미지로 변환합니다.",
    "icon": "🖼",
    "category": "image",
    "path": "converters/png-gif/index.html",
    "status": "ready",
    "accept": [
      ".png"
    ],
    "output": "gif",
    "sourceFormat": "PNG",
    "targetFormat": "GIF",
    "priority": 118.6,
    "generatedBy": "png-popular-pack-2",
    "accessLevel": "free",
    "trialAvailable": false,
    "audience": "일반 사용자",
    "featured": true
  },
  {
    "id": "png-bmp",
    "title": "PNG → BMP",
    "description": "PNG를 구형 프로그램 호환 BMP 형식으로 변환합니다.",
    "icon": "🖼",
    "category": "image",
    "path": "converters/png-bmp/index.html",
    "status": "ready",
    "accept": [
      ".png"
    ],
    "output": "bmp",
    "sourceFormat": "PNG",
    "targetFormat": "BMP",
    "priority": 118.5,
    "generatedBy": "png-popular-pack-2",
    "accessLevel": "free",
    "trialAvailable": false,
    "audience": "일반 사용자",
    "featured": false
  },
  {
    "id": "png-jfif",
    "title": "PNG → JFIF",
    "description": "PNG를 호환성 높은 JFIF 이미지로 변환합니다.",
    "icon": "🖼",
    "category": "image",
    "path": "converters/png-jfif/index.html",
    "status": "ready",
    "accept": [
      ".png"
    ],
    "output": "jfif",
    "sourceFormat": "PNG",
    "targetFormat": "JFIF",
    "priority": 118.4,
    "generatedBy": "png-popular-pack-2",
    "accessLevel": "free",
    "trialAvailable": false,
    "audience": "일반 사용자",
    "featured": false
  },
  {
    "id": "png-base64",
    "title": "PNG → Base64",
    "description": "PNG를 Base64 데이터 URL 텍스트로 변환합니다.",
    "icon": "🖼",
    "category": "image",
    "path": "converters/png-base64/index.html",
    "status": "ready",
    "accept": [
      ".png"
    ],
    "output": "base64",
    "sourceFormat": "PNG",
    "targetFormat": "BASE64",
    "priority": 118.3,
    "generatedBy": "png-popular-pack-2",
    "accessLevel": "free",
    "trialAvailable": false,
    "audience": "일반 사용자",
    "featured": false
  },
  {
    "id": "png-html",
    "title": "PNG → HTML",
    "description": "PNG를 포함한 독립 실행형 HTML 갤러리를 만듭니다.",
    "icon": "🖼",
    "category": "image",
    "path": "converters/png-html/index.html",
    "status": "ready",
    "accept": [
      ".png"
    ],
    "output": "html",
    "sourceFormat": "PNG",
    "targetFormat": "HTML",
    "priority": 118.2,
    "generatedBy": "png-popular-pack-2",
    "accessLevel": "free",
    "trialAvailable": false,
    "audience": "일반 사용자",
    "featured": false
  },
  {
    "id": "png-pnm",
    "title": "PNG → PNM",
    "description": "PNG를 Netpbm 계열 범용 PNM(P6) 이미지로 변환합니다.",
    "icon": "🖼",
    "category": "image",
    "path": "converters/png-pnm/index.html",
    "status": "ready",
    "accept": [
      ".png"
    ],
    "output": "pnm",
    "sourceFormat": "PNG",
    "targetFormat": "PNM",
    "priority": 118.2,
    "generatedBy": "png-netpbm-pack",
    "accessLevel": "professional",
    "trialAvailable": true,
    "audience": "전문가",
    "featured": false
  },
  {
    "id": "png-zip",
    "title": "PNG → ZIP",
    "description": "여러 PNG 원본을 한 개의 ZIP 파일로 묶습니다.",
    "icon": "🖼",
    "category": "image",
    "path": "converters/png-zip/index.html",
    "status": "ready",
    "accept": [
      ".png"
    ],
    "output": "zip",
    "sourceFormat": "PNG",
    "targetFormat": "ZIP",
    "priority": 118.1,
    "generatedBy": "png-popular-pack-2",
    "accessLevel": "free",
    "trialAvailable": false,
    "audience": "일반 사용자",
    "featured": true
  },
  {
    "id": "png-ppm",
    "title": "PNG → PPM",
    "description": "PNG를 무손실 RGB Portable Pixmap(PPM) 형식으로 변환합니다.",
    "icon": "🖼",
    "category": "image",
    "path": "converters/png-ppm/index.html",
    "status": "ready",
    "accept": [
      ".png"
    ],
    "output": "ppm",
    "sourceFormat": "PNG",
    "targetFormat": "PPM",
    "priority": 118.1,
    "generatedBy": "png-netpbm-pack",
    "accessLevel": "professional",
    "trialAvailable": true,
    "audience": "전문가",
    "featured": false
  },
  {
    "id": "jpg-png",
    "title": "JPG → PNG",
    "description": "JPG 이미지를 고품질 PNG 형식으로 변환합니다.",
    "icon": "🖼",
    "category": "image",
    "path": "converters/jpg-png/index.html",
    "status": "ready",
    "accept": [
      ".jpg",
      ".jpeg"
    ],
    "output": "png",
    "sourceFormat": "JPG",
    "targetFormat": "PNG",
    "priority": 118,
    "generatedBy": "image-converter-registry",
    "accessLevel": "free",
    "trialAvailable": false,
    "audience": "일반 사용자",
    "featured": true
  },
  {
    "id": "png-pgm",
    "title": "PNG → PGM",
    "description": "PNG를 그레이스케일 Portable Graymap(PGM) 형식으로 변환합니다.",
    "icon": "🖼",
    "category": "image",
    "path": "converters/png-pgm/index.html",
    "status": "ready",
    "accept": [
      ".png"
    ],
    "output": "pgm",
    "sourceFormat": "PNG",
    "targetFormat": "PGM",
    "priority": 118.0,
    "generatedBy": "png-netpbm-pack",
    "accessLevel": "professional",
    "trialAvailable": true,
    "audience": "전문가",
    "featured": false
  },
  {
    "id": "png-pbm",
    "title": "PNG → PBM",
    "description": "PNG를 흑백 1비트 Portable Bitmap(PBM) 형식으로 변환합니다.",
    "icon": "🖼",
    "category": "image",
    "path": "converters/png-pbm/index.html",
    "status": "ready",
    "accept": [
      ".png"
    ],
    "output": "pbm",
    "sourceFormat": "PNG",
    "targetFormat": "PBM",
    "priority": 117.9,
    "generatedBy": "png-netpbm-pack",
    "accessLevel": "professional",
    "trialAvailable": true,
    "audience": "전문가",
    "featured": false
  },
  {
    "id": "png-pam",
    "title": "PNG → PAM",
    "description": "PNG의 RGBA 투명도를 보존해 Portable Arbitrary Map(PAM)으로 변환합니다.",
    "icon": "🖼",
    "category": "image",
    "path": "converters/png-pam/index.html",
    "status": "ready",
    "accept": [
      ".png"
    ],
    "output": "pam",
    "sourceFormat": "PNG",
    "targetFormat": "PAM",
    "priority": 117.8,
    "generatedBy": "png-netpbm-pack",
    "accessLevel": "professional",
    "trialAvailable": true,
    "audience": "전문가",
    "featured": false
  },
  {
    "id": "png-xbm",
    "title": "PNG → XBM",
    "description": "PNG를 C 소스에 삽입 가능한 1비트 X BitMap(XBM) 형식으로 변환합니다.",
    "icon": "🖼",
    "category": "image",
    "path": "converters/png-xbm/index.html",
    "status": "ready",
    "accept": [
      ".png"
    ],
    "output": "xbm",
    "sourceFormat": "PNG",
    "targetFormat": "XBM",
    "priority": 117.7,
    "generatedBy": "png-netpbm-pack",
    "accessLevel": "professional",
    "trialAvailable": true,
    "audience": "전문가",
    "featured": false
  },
  {
    "id": "jpg-webp",
    "title": "JPG → WEBP",
    "description": "JPG 이미지를 고품질 WEBP 형식으로 변환합니다.",
    "icon": "🖼",
    "category": "image",
    "path": "converters/jpg-webp/index.html",
    "status": "ready",
    "accept": [
      ".jpg",
      ".jpeg"
    ],
    "output": "webp",
    "sourceFormat": "JPG",
    "targetFormat": "WEBP",
    "priority": 117,
    "generatedBy": "image-converter-registry",
    "accessLevel": "free",
    "trialAvailable": false,
    "audience": "일반 사용자",
    "featured": false
  },
  {
    "id": "webp-png",
    "title": "WEBP → PNG",
    "description": "WEBP 이미지를 고품질 PNG 형식으로 변환합니다.",
    "icon": "🖼",
    "category": "image",
    "path": "converters/webp-png/index.html",
    "status": "ready",
    "accept": [
      ".webp"
    ],
    "output": "png",
    "sourceFormat": "WEBP",
    "targetFormat": "PNG",
    "priority": 116,
    "generatedBy": "image-converter-registry",
    "accessLevel": "free",
    "trialAvailable": false,
    "audience": "일반 사용자",
    "featured": false
  },
  {
    "id": "webp-jpg",
    "title": "WEBP → JPG",
    "description": "WEBP 이미지를 고품질 JPG 형식으로 변환합니다.",
    "icon": "🖼",
    "category": "image",
    "path": "converters/webp-jpg/index.html",
    "status": "ready",
    "accept": [
      ".webp"
    ],
    "output": "jpg",
    "sourceFormat": "WEBP",
    "targetFormat": "JPG",
    "priority": 115,
    "generatedBy": "image-converter-registry",
    "accessLevel": "free",
    "trialAvailable": false,
    "audience": "일반 사용자",
    "featured": false
  },
  {
    "id": "avif-jpg",
    "title": "AVIF → JPG",
    "description": "AVIF 이미지를 고품질 JPG 형식으로 변환합니다.",
    "icon": "🖼",
    "category": "image",
    "path": "converters/avif-jpg/index.html",
    "status": "ready",
    "accept": [
      ".avif"
    ],
    "output": "jpg",
    "sourceFormat": "AVIF",
    "targetFormat": "JPG",
    "priority": 114,
    "generatedBy": "image-converter-registry",
    "accessLevel": "professional",
    "trialAvailable": true,
    "audience": "전문가",
    "featured": false
  },
  {
    "id": "avif-png",
    "title": "AVIF → PNG",
    "description": "AVIF 이미지를 고품질 PNG 형식으로 변환합니다.",
    "icon": "🖼",
    "category": "image",
    "path": "converters/avif-png/index.html",
    "status": "ready",
    "accept": [
      ".avif"
    ],
    "output": "png",
    "sourceFormat": "AVIF",
    "targetFormat": "PNG",
    "priority": 113,
    "generatedBy": "image-converter-registry",
    "accessLevel": "professional",
    "trialAvailable": true,
    "audience": "전문가",
    "featured": false
  },
  {
    "id": "png-avif",
    "title": "PNG → AVIF",
    "description": "PNG를 차세대 고압축 AVIF 이미지로 변환합니다.",
    "icon": "🖼",
    "category": "image",
    "path": "converters/png-avif/index.html",
    "status": "ready",
    "accept": [
      ".png"
    ],
    "output": "avif",
    "sourceFormat": "PNG",
    "targetFormat": "AVIF",
    "priority": 112.4,
    "generatedBy": "png-professional-codec-pack-2",
    "accessLevel": "professional",
    "trialAvailable": true,
    "audience": "전문가",
    "featured": false
  },
  {
    "id": "png-tga",
    "title": "PNG → TGA",
    "description": "PNG를 게임·3D 그래픽 도구에서 사용하는 32비트 TGA 형식으로 변환합니다.",
    "icon": "🖼",
    "category": "image",
    "path": "converters/png-tga/index.html",
    "status": "ready",
    "accept": [
      ".png"
    ],
    "output": "tga",
    "sourceFormat": "PNG",
    "targetFormat": "TGA",
    "priority": 112.3,
    "generatedBy": "png-professional-codec-pack-1",
    "accessLevel": "professional",
    "trialAvailable": true,
    "audience": "전문가",
    "featured": false
  },
  {
    "id": "png-dds",
    "title": "PNG → DDS",
    "description": "PNG를 게임·3D 도구용 BGRA8 DDS 텍스처로 변환합니다.",
    "icon": "🖼",
    "category": "image",
    "path": "converters/png-dds/index.html",
    "status": "ready",
    "accept": [
      ".png"
    ],
    "output": "dds",
    "sourceFormat": "PNG",
    "targetFormat": "DDS",
    "priority": 112.3,
    "generatedBy": "png-professional-codec-pack-2",
    "accessLevel": "professional",
    "trialAvailable": true,
    "audience": "전문가",
    "featured": false
  },
  {
    "id": "png-tiff",
    "title": "PNG → TIFF",
    "description": "PNG를 인쇄·스캔·고해상도 보관에 적합한 무압축 RGBA TIFF로 변환합니다.",
    "icon": "🖼",
    "category": "image",
    "path": "converters/png-tiff/index.html",
    "status": "ready",
    "accept": [
      ".png"
    ],
    "output": "tiff",
    "sourceFormat": "PNG",
    "targetFormat": "TIFF",
    "priority": 112.2,
    "generatedBy": "png-professional-codec-pack-1",
    "accessLevel": "professional",
    "trialAvailable": true,
    "audience": "전문가",
    "featured": false
  },
  {
    "id": "png-psd",
    "title": "PNG → PSD",
    "description": "PNG를 단일 평면 RGBA PSD 파일로 변환합니다.",
    "icon": "🖼",
    "category": "image",
    "path": "converters/png-psd/index.html",
    "status": "ready",
    "accept": [
      ".png"
    ],
    "output": "psd",
    "sourceFormat": "PNG",
    "targetFormat": "PSD",
    "priority": 112.2,
    "generatedBy": "png-professional-codec-pack-2",
    "accessLevel": "professional",
    "trialAvailable": true,
    "audience": "전문가",
    "featured": false
  },
  {
    "id": "png-pcx",
    "title": "PNG → PCX",
    "description": "PNG를 레거시 그래픽·출판 프로그램 호환용 24비트 PCX 형식으로 변환합니다.",
    "icon": "🖼",
    "category": "image",
    "path": "converters/png-pcx/index.html",
    "status": "ready",
    "accept": [
      ".png"
    ],
    "output": "pcx",
    "sourceFormat": "PNG",
    "targetFormat": "PCX",
    "priority": 112.1,
    "generatedBy": "png-professional-codec-pack-1",
    "accessLevel": "professional",
    "trialAvailable": true,
    "audience": "전문가",
    "featured": false
  },
  {
    "id": "png-cur",
    "title": "PNG → CUR",
    "description": "PNG를 Windows 마우스 커서용 다중 크기 CUR 파일로 변환합니다.",
    "icon": "🖼",
    "category": "image",
    "path": "converters/png-cur/index.html",
    "status": "ready",
    "accept": [
      ".png"
    ],
    "output": "cur",
    "sourceFormat": "PNG",
    "targetFormat": "CUR",
    "priority": 112.0,
    "generatedBy": "png-professional-codec-pack-1",
    "accessLevel": "professional",
    "trialAvailable": true,
    "audience": "전문가",
    "featured": false
  },
  {
    "id": "avif-webp",
    "title": "AVIF → WEBP",
    "description": "AVIF 이미지를 고품질 WEBP 형식으로 변환합니다.",
    "icon": "🖼",
    "category": "image",
    "path": "converters/avif-webp/index.html",
    "status": "ready",
    "accept": [
      ".avif"
    ],
    "output": "webp",
    "sourceFormat": "AVIF",
    "targetFormat": "WEBP",
    "priority": 112,
    "generatedBy": "image-converter-registry",
    "accessLevel": "professional",
    "trialAvailable": true,
    "audience": "전문가",
    "featured": false
  },
  {
    "id": "gif-jpg",
    "title": "GIF → JPG",
    "description": "GIF 이미지를 JPG 형식으로 변환합니다. 애니메이션 GIF는 첫 번째 프레임을 변환합니다.",
    "icon": "🖼",
    "category": "image",
    "path": "converters/gif-jpg/index.html",
    "status": "ready",
    "accept": [
      ".gif"
    ],
    "output": "jpg",
    "sourceFormat": "GIF",
    "targetFormat": "JPG",
    "priority": 111,
    "generatedBy": "image-converter-registry",
    "accessLevel": "free",
    "trialAvailable": false,
    "audience": "일반 사용자",
    "featured": false
  },
  {
    "id": "gif-png",
    "title": "GIF → PNG",
    "description": "GIF 이미지를 PNG 형식으로 변환합니다. 애니메이션 GIF는 첫 번째 프레임을 변환합니다.",
    "icon": "🖼",
    "category": "image",
    "path": "converters/gif-png/index.html",
    "status": "ready",
    "accept": [
      ".gif"
    ],
    "output": "png",
    "sourceFormat": "GIF",
    "targetFormat": "PNG",
    "priority": 110,
    "generatedBy": "image-converter-registry",
    "accessLevel": "free",
    "trialAvailable": false,
    "audience": "일반 사용자",
    "featured": false
  },
  {
    "id": "gif-webp",
    "title": "GIF → WEBP",
    "description": "GIF 이미지를 WEBP 형식으로 변환합니다. 애니메이션 GIF는 첫 번째 프레임을 변환합니다.",
    "icon": "🖼",
    "category": "image",
    "path": "converters/gif-webp/index.html",
    "status": "ready",
    "accept": [
      ".gif"
    ],
    "output": "webp",
    "sourceFormat": "GIF",
    "targetFormat": "WEBP",
    "priority": 109,
    "generatedBy": "image-converter-registry",
    "accessLevel": "professional",
    "trialAvailable": true,
    "audience": "전문가",
    "featured": false
  },
  {
    "id": "bmp-jpg",
    "title": "BMP → JPG",
    "description": "BMP 이미지를 고품질 JPG 형식으로 변환합니다.",
    "icon": "🖼",
    "category": "image",
    "path": "converters/bmp-jpg/index.html",
    "status": "ready",
    "accept": [
      ".bmp"
    ],
    "output": "jpg",
    "sourceFormat": "BMP",
    "targetFormat": "JPG",
    "priority": 108,
    "generatedBy": "image-converter-registry",
    "accessLevel": "free",
    "trialAvailable": false,
    "audience": "일반 사용자",
    "featured": false
  },
  {
    "id": "bmp-png",
    "title": "BMP → PNG",
    "description": "BMP 이미지를 고품질 PNG 형식으로 변환합니다.",
    "icon": "🖼",
    "category": "image",
    "path": "converters/bmp-png/index.html",
    "status": "ready",
    "accept": [
      ".bmp"
    ],
    "output": "png",
    "sourceFormat": "BMP",
    "targetFormat": "PNG",
    "priority": 107,
    "generatedBy": "image-converter-registry",
    "accessLevel": "free",
    "trialAvailable": false,
    "audience": "일반 사용자",
    "featured": false
  },
  {
    "id": "bmp-webp",
    "title": "BMP → WEBP",
    "description": "BMP 이미지를 고품질 WEBP 형식으로 변환합니다.",
    "icon": "🖼",
    "category": "image",
    "path": "converters/bmp-webp/index.html",
    "status": "ready",
    "accept": [
      ".bmp"
    ],
    "output": "webp",
    "sourceFormat": "BMP",
    "targetFormat": "WEBP",
    "priority": 106,
    "generatedBy": "image-converter-registry",
    "accessLevel": "professional",
    "trialAvailable": true,
    "audience": "전문가",
    "featured": false
  },
  {
    "id": "svg-jpg",
    "title": "SVG → JPG",
    "description": "SVG 벡터 이미지를 고품질 JPG 형식으로 변환합니다.",
    "icon": "🖼",
    "category": "image",
    "path": "converters/svg-jpg/index.html",
    "status": "ready",
    "accept": [
      ".svg"
    ],
    "output": "jpg",
    "sourceFormat": "SVG",
    "targetFormat": "JPG",
    "priority": 105,
    "generatedBy": "image-converter-registry",
    "accessLevel": "professional",
    "trialAvailable": true,
    "audience": "전문가",
    "featured": false
  },
  {
    "id": "svg-png",
    "title": "SVG → PNG",
    "description": "SVG 벡터 이미지를 고품질 PNG 형식으로 변환합니다.",
    "icon": "🖼",
    "category": "image",
    "path": "converters/svg-png/index.html",
    "status": "ready",
    "accept": [
      ".svg"
    ],
    "output": "png",
    "sourceFormat": "SVG",
    "targetFormat": "PNG",
    "priority": 104,
    "generatedBy": "image-converter-registry",
    "accessLevel": "free",
    "trialAvailable": false,
    "audience": "일반 사용자",
    "featured": false
  },
  {
    "id": "svg-webp",
    "title": "SVG → WEBP",
    "description": "SVG 벡터 이미지를 고품질 WEBP 형식으로 변환합니다.",
    "icon": "🖼",
    "category": "image",
    "path": "converters/svg-webp/index.html",
    "status": "ready",
    "accept": [
      ".svg"
    ],
    "output": "webp",
    "sourceFormat": "SVG",
    "targetFormat": "WEBP",
    "priority": 103,
    "generatedBy": "image-converter-registry",
    "accessLevel": "professional",
    "trialAvailable": true,
    "audience": "전문가",
    "featured": false
  }
]